Workbook

Sheet Ringkasan Keuangan - Soal No.1
B2: INSTRUKSI SOAL NO. 1: Isilah kolom berwarna ungu pada tabel di bawah ini dengan menggunakan rumus / formula (Tabel Ringkasan Keuangan ini berdasarkan Penjualan dari pembayaran yang sudah lunas, Pembelian untuk Operasional Penjualan, Gaji Karyawan, dan Biaya Transportasi)
B4: Kategori / Bulan | D4: January 2025 | E4: February 2025 | F4: March 2025 | G4: April 2025 | H4: May 2025 | I4: June 2025 | J4: Total
B5: Penjualan | D5: =SUM(D6:D12) -> 29559100 | E5: =SUM(E6:E12) -> 27340681 | F5: =SUM(F6:F12) -> 25608650 | G5: =SUM(G6:G12) -> 28010520 | H5: =SUM(H6:H12) -> 33274942 | I5: =SUM(I6:I12) -> 26697450 | J5: =SUM(D5:I5) -> 1.7049134e+08
B6: 1 | C6: Fixing | D6: =SUMIFS('Data Penjualan'!$D:$D,'Data Penjualan'!$C:$C,"Fixing",'Data Penjualan'!$B:$B,"January 2025") -> 3772750 | E6: =SUMIFS('Data Penjualan'!$D:$D,'Data Penjualan'!$C:$C,"Fixing",'Data Penjualan'!$B:$B,"February 2025") -> 3189250 | F6: =SUMIFS('Data Penjualan'!$D:$D,'Data Penjualan'!$C:$C,"Fixing",'Data Penjualan'!$B:$B,"March 2025") -> 3136250 | G6: =SUMIFS('Data Penjualan'!$D:$D,'Data Penjualan'!$C:$C,"Fixing",'Data Penjualan'!$B:$B,"April 2025") -> 4145619.5 | H6: =SUMIFS('Data Penjualan'!$D:$D,'Data Penjualan'!$C:$C,"Fixing",'Data Penjualan'!$B:$B,"May 2025") -> 3630666.7 | I6: =SUMIFS('Data Penjualan'!$D:$D,'Data Penjualan'!$C:$C,"Fixing",'Data Penjualan'!$B:$B,"June 2025") -> 3445800 | J6: =SUM(D6:I6) -> 21320336
B7: 2 | C7: Lainnya | D7: =SUMIFS('Data Penjualan'!$D:$D,'Data Penjualan'!$C:$C,"Lainnya",'Data Penjualan'!$B:$B,"January 2025") -> 1355150 | E7: =SUMIFS('Data Penjualan'!$D:$D,'Data Penjualan'!$C:$C,"Lainnya",'Data Penjualan'!$B:$B,"February 2025") -> 971230.45 | F7: =SUMIFS('Data Penjualan'!$D:$D,'Data Penjualan'!$C:$C,"Lainnya",'Data Penjualan'!$B:$B,"March 2025") -> 832900 | G7: =SUMIFS('Data Penjualan'!$D:$D,'Data Penjualan'!$C:$C,"Lainnya",'Data Penjualan'!$B:$B,"April 2025") -> 897500 | H7: =SUMIFS('Data Penjualan'!$D:$D,'Data Penjualan'!$C:$C,"Lainnya",'Data Penjualan'!$B:$B,"May 2025") -> 793000 | I7: =SUMIFS('Data Penjualan'!$D:$D,'Data Penjualan'!$C:$C,"Lainnya",'Data Penjualan'!$B:$B,"June 2025") -> 627250 | J7: =SUM(D7:I7) -> 5477030.5
B8: 3 | C8: Cleaning | D8: =SUMIFS('Data Penjualan'!$D:$D,'Data Penjualan'!$C:$C,"Cleaning",'Data Penjualan'!$B:$B,"January 2025") -> 3957500 | E8: =SUMIFS('Data Penjualan'!$D:$D,'Data Penjualan'!$C:$C,"Cleaning",'Data Penjualan'!$B:$B,"February 2025") -> 3862500 | F8: =SUMIFS('Data Penjualan'!$D:$D,'Data Penjualan'!$C:$C,"Cleaning",'Data Penjualan'!$B:$B,"March 2025") -> 4229250 | G8: =SUMIFS('Data Penjualan'!$D:$D,'Data Penjualan'!$C:$C,"Cleaning",'Data Penjualan'!$B:$B,"April 2025") -> 3686250 | H8: =SUMIFS('Data Penjualan'!$D:$D,'Data Penjualan'!$C:$C,"Cleaning",'Data Penjualan'!$B:$B,"May 2025") -> 4037250 | I8: =SUMIFS('Data Penjualan'!$D:$D,'Data Penjualan'!$C:$C,"Cleaning",'Data Penjualan'!$B:$B,"June 2025") -> 3002500 | J8: =SUM(D8:I8) -> 22775250
B9: 4 | C9: AC | D9: =SUMIFS('Data Penjualan'!$D:$D,'Data Penjualan'!$C:$C,"AC",'Data Penjualan'!$B:$B,"January 2025") -> 1990000 | E9: =SUMIFS('Data Penjualan'!$D:$D,'Data Penjualan'!$C:$C,"AC",'Data Penjualan'!$B:$B,"February 2025") -> 2027500 | F9: =SUMIFS('Data Penjualan'!$D:$D,'Data Penjualan'!$C:$C,"AC",'Data Penjualan'!$B:$B,"March 2025") -> 1892500 | G9: =SUMIFS('Data Penjualan'!$D:$D,'Data Penjualan'!$C:$C,"AC",'Data Penjualan'!$B:$B,"April 2025") -> 2141750 | H9: =SUMIFS('Data Penjualan'!$D:$D,'Data Penjualan'!$C:$C,"AC",'Data Penjualan'!$B:$B,"May 2025") -> 2519500 | I9: =SUMIFS('Data Penjualan'!$D:$D,'Data Penjualan'!$C:$C,"AC",'Data Penjualan'!$B:$B,"June 2025") -> 2108500 | J9: =SUM(D9:I9) -> 12679750
B10: 5 | C10: Material | D10: =SUMIFS('Data Penjualan'!$D:$D,'Data Penjualan'!$C:$C,"Material",'Data Penjualan'!$B:$B,"January 2025") -> 8705699.6 | E10: =SUMIFS('Data Penjualan'!$D:$D,'Data Penjualan'!$C:$C,"Material",'Data Penjualan'!$B:$B,"February 2025") -> 7434200.4 | F10: =SUMIFS('Data Penjualan'!$D:$D,'Data Penjualan'!$C:$C,"Material",'Data Penjualan'!$B:$B,"March 2025") -> 5876750 | G10: =SUMIFS('Data Penjualan'!$D:$D,'Data Penjualan'!$C:$C,"Material",'Data Penjualan'!$B:$B,"April 2025") -> 8018400 | H10: =SUMIFS('Data Penjualan'!$D:$D,'Data Penjualan'!$C:$C,"Material",'Data Penjualan'!$B:$B,"May 2025") -> 11188525 | I10: =SUMIFS('Data Penjualan'!$D:$D,'Data Penjualan'!$C:$C,"Material",'Data Penjualan'!$B:$B,"June 2025") -> 6205400 | J10: =SUM(D10:I10) -> 47428975
B11: 6 | C11: Field Assistant | D11: =SUMIFS('Data Penjualan'!$D:$D,'Data Penjualan'!$C:$C,"Field Assistant",'Data Penjualan'!$B:$B,"January 2025") -> 8948000 | E11: =SUMIFS('Data Penjualan'!$D:$D,'Data Penjualan'!$C:$C,"Field Assistant",'Data Penjualan'!$B:$B,"February 2025") -> 9036000 | F11: =SUMIFS('Data Penjualan'!$D:$D,'Data Penjualan'!$C:$C,"Field Assistant",'Data Penjualan'!$B:$B,"March 2025") -> 8876000 | G11: =SUMIFS('Data Penjualan'!$D:$D,'Data Penjualan'!$C:$C,"Field Assistant",'Data Penjualan'!$B:$B,"April 2025") -> 8196000 | H11: =SUMIFS('Data Penjualan'!$D:$D,'Data Penjualan'!$C:$C,"Field Assistant",'Data Penjualan'!$B:$B,"May 2025") -> 9636000 | I11: =SUMIFS('Data Penjualan'!$D:$D,'Data Penjualan'!$C:$C,"Field Assistant",'Data Penjualan'!$B:$B,"June 2025") -> 9868000 | J11: =SUM(D11:I11) -> 54560000
B12: 7 | C12: Photographer | D12: =SUMIFS('Data Penjualan'!$D:$D,'Data Penjualan'!$C:$C,"Photographer",'Data Penjualan'!$B:$B,"January 2025") -> 830000 | E12: =SUMIFS('Data Penjualan'!$D:$D,'Data Penjualan'!$C:$C,"Photographer",'Data Penjualan'!$B:$B,"February 2025") -> 820000 | F12: =SUMIFS('Data Penjualan'!$D:$D,'Data Penjualan'!$C:$C,"Photographer",'Data Penjualan'!$B:$B,"March 2025") -> 765000 | G12: =SUMIFS('Data Penjualan'!$D:$D,'Data Penjualan'!$C:$C,"Photographer",'Data Penjualan'!$B:$B,"April 2025") -> 925000 | H12: =SUMIFS('Data Penjualan'!$D:$D,'Data Penjualan'!$C:$C,"Photographer",'Data Penjualan'!$B:$B,"May 2025") -> 1470000 | I12: =SUMIFS('Data Penjualan'!$D:$D,'Data Penjualan'!$C:$C,"Photographer",'Data Penjualan'!$B:$B,"June 2025") -> 1440000 | J12: =SUM(D12:I12) -> 6250000
B14: Gaji Karyawan | D14: =SUM(D15:D20) -> 11032859 | E14: =SUM(E15:E20) -> 11397067 | F14: =SUM(F15:F20) -> 11653655 | G14: =SUM(G15:G20) -> 12578899 | H14: =SUM(H15:H20) -> 13557386 | I14: =SUM(I15:I20) -> 14337578 | J14: =SUM(D14:I14) -> 74557444
B15: 1 | C15: Admin | D15: =SUMIFS('Data Gaji'!$C:$C,'Data Gaji'!$F:$F,"Admin",'Data Gaji'!$A:$A,"January 2025") -> 1284948.9 | E15: =SUMIFS('Data Gaji'!$C:$C,'Data Gaji'!$F:$F,"Admin",'Data Gaji'!$A:$A,"February 2025") -> 1336090.3 | F15: =SUMIFS('Data Gaji'!$C:$C,'Data Gaji'!$F:$F,"Admin",'Data Gaji'!$A:$A,"March 2025") -> 1208670.8 | G15: =SUMIFS('Data Gaji'!$C:$C,'Data Gaji'!$F:$F,"Admin",'Data Gaji'!$A:$A,"April 2025") -> 1272670.4 | H15: =SUMIFS('Data Gaji'!$C:$C,'Data Gaji'!$F:$F,"Admin",'Data Gaji'!$A:$A,"May 2025") -> 1202324 | I15: =SUMIFS('Data Gaji'!$C:$C,'Data Gaji'!$F:$F,"Admin",'Data Gaji'!$A:$A,"June 2025") -> 1244627.6 | J15: =SUM(D15:I15) -> 7549332
B16: 2 | C16: Teknisi AC | D16: =SUMIFS('Data Gaji'!$C:$C,'Data Gaji'!$F:$F,"Teknisi AC",'Data Gaji'!$A:$A,"January 2025") -> 2480445.8 | E16: =SUMIFS('Data Gaji'!$C:$C,'Data Gaji'!$F:$F,"Teknisi AC",'Data Gaji'!$A:$A,"February 2025") -> 2395768.1 | F16: =SUMIFS('Data Gaji'!$C:$C,'Data Gaji'!$F:$F,"Teknisi AC",'Data Gaji'!$A:$A,"March 2025") -> 2415424.8 | G16: =SUMIFS('Data Gaji'!$C:$C,'Data Gaji'!$F:$F,"Teknisi AC",'Data Gaji'!$A:$A,"April 2025") -> 2578300.2 | H16: =SUMIFS('Data Gaji'!$C:$C,'Data Gaji'!$F:$F,"Teknisi AC",'Data Gaji'!$A:$A,"May 2025") -> 2622697.4 | I16: =SUMIFS('Data Gaji'!$C:$C,'Data Gaji'!$F:$F,"Teknisi AC",'Data Gaji'!$A:$A,"June 2025") -> 2575503.7 | J16: =SUM(D16:I16) -> 15068140
B17: 3 | C17: Asisten Lapangan | D17: =SUMIFS('Data Gaji'!$C:$C,'Data Gaji'!$F:$F,"Asisten Lapangan",'Data Gaji'!$A:$A,"January 2025") -> 3521705.3 | E17: =SUMIFS('Data Gaji'!$C:$C,'Data Gaji'!$F:$F,"Asisten Lapangan",'Data Gaji'!$A:$A,"February 2025") -> 3591611.5 | F17: =SUMIFS('Data Gaji'!$C:$C,'Data Gaji'!$F:$F,"Asisten Lapangan",'Data Gaji'!$A:$A,"March 2025") -> 3544001.9 | G17: =SUMIFS('Data Gaji'!$C:$C,'Data Gaji'!$F:$F,"Asisten Lapangan",'Data Gaji'!$A:$A,"April 2025") -> 3876571.7 | H17: =SUMIFS('Data Gaji'!$C:$C,'Data Gaji'!$F:$F,"Asisten Lapangan",'Data Gaji'!$A:$A,"May 2025") -> 4072889.7 | I17: =SUMIFS('Data Gaji'!$C:$C,'Data Gaji'!$F:$F,"Asisten Lapangan",'Data Gaji'!$A:$A,"June 2025") -> 4170487.6 | J17: =SUM(D17:I17) -> 22777268
B18: 4 | C18: Teknisi Kebersihan | D18: =SUMIFS('Data Gaji'!$C:$C,'Data Gaji'!$F:$F,"Teknisi Kebersihan",'Data Gaji'!$A:$A,"January 2025") -> 1212455.1 | E18: =SUMIFS('Data Gaji'!$C:$C,'Data Gaji'!$F:$F,"Teknisi Kebersihan",'Data Gaji'!$A:$A,"February 2025") -> 1315213.2 | F18: =SUMIFS('Data Gaji'!$C:$C,'Data Gaji'!$F:$F,"Teknisi Kebersihan",'Data Gaji'!$A:$A,"March 2025") -> 1235229.4 | G18: =SUMIFS('Data Gaji'!$C:$C,'Data Gaji'!$F:$F,"Teknisi Kebersihan",'Data Gaji'!$A:$A,"April 2025") -> 1506422.8 | H18: =SUMIFS('Data Gaji'!$C:$C,'Data Gaji'!$F:$F,"Teknisi Kebersihan",'Data Gaji'!$A:$A,"May 2025") -> 1844912.1 | I18: =SUMIFS('Data Gaji'!$C:$C,'Data Gaji'!$F:$F,"Teknisi Kebersihan",'Data Gaji'!$A:$A,"June 2025") -> 1955500.2 | J18: =SUM(D18:I18) -> 9069732.9
B19: 5 | C19: Teknisi Perbaikan | D19: =SUMIFS('Data Gaji'!$C:$C,'Data Gaji'!$F:$F,"Teknisi Perbaikan",'Data Gaji'!$A:$A,"January 2025") -> 2182890.7 | E19: =SUMIFS('Data Gaji'!$C:$C,'Data Gaji'!$F:$F,"Teknisi Perbaikan",'Data Gaji'!$A:$A,"February 2025") -> 2401729.2 | F19: =SUMIFS('Data Gaji'!$C:$C,'Data Gaji'!$F:$F,"Teknisi Perbaikan",'Data Gaji'!$A:$A,"March 2025") -> 2692963.7 | G19: =SUMIFS('Data Gaji'!$C:$C,'Data Gaji'!$F:$F,"Teknisi Perbaikan",'Data Gaji'!$A:$A,"April 2025") -> 2793469.4 | H19: =SUMIFS('Data Gaji'!$C:$C,'Data Gaji'!$F:$F,"Teknisi Perbaikan",'Data Gaji'!$A:$A,"May 2025") -> 3210270.2 | I19: =SUMIFS('Data Gaji'!$C:$C,'Data Gaji'!$F:$F,"Teknisi Perbaikan",'Data Gaji'!$A:$A,"June 2025") -> 3755632.6 | J19: =SUM(D19:I19) -> 17036956
B20: 6 | C20: Fotografer | D20: =SUMIFS('Data Gaji'!$C:$C,'Data Gaji'!$F:$F,"Fotografer",'Data Gaji'!$A:$A,"January 2025") -> 350413 | E20: =SUMIFS('Data Gaji'!$C:$C,'Data Gaji'!$F:$F,"Fotografer",'Data Gaji'!$A:$A,"February 2025") -> 356654.9 | F20: =SUMIFS('Data Gaji'!$C:$C,'Data Gaji'!$F:$F,"Fotografer",'Data Gaji'!$A:$A,"March 2025") -> 557364.6 | G20: =SUMIFS('Data Gaji'!$C:$C,'Data Gaji'!$F:$F,"Fotografer",'Data Gaji'!$A:$A,"April 2025") -> 551464.5 | H20: =SUMIFS('Data Gaji'!$C:$C,'Data Gaji'!$F:$F,"Fotografer",'Data Gaji'!$A:$A,"May 2025") -> 604292.5 | I20: =SUMIFS('Data Gaji'!$C:$C,'Data Gaji'!$F:$F,"Fotografer",'Data Gaji'!$A:$A,"June 2025") -> 635825.8 | J20: =SUM(D20:I20) -> 3056015.3
B22: Biaya Penjualan | D22: =SUM(D23:D25) -> 10021271 | E22: =SUM(E23:E25) -> 9233173.9 | F22: =SUM(F23:F25) -> 7902103 | G22: =SUM(G23:G25) -> 7105892.6 | H22: =SUM(H23:H25) -> 8591464.6 | I22: =SUM(I23:I25) -> 9403263.5 | J22: =SUM(D22:I22) -> 52257169
B23: 1 | C23: SPK | D23: =SUMIFS('Data Pembelian untuk Operasiona'!$D:$D,'Data Pembelian untuk Operasiona'!$E:$E,"SPK",'Data Pembelian untuk Operasiona'!$A:$A,"January 2025") -> 7462306.6 | E23: =SUMIFS('Data Pembelian untuk Operasiona'!$D:$D,'Data Pembelian untuk Operasiona'!$E:$E,"SPK",'Data Pembelian untuk Operasiona'!$A:$A,"February 2025") -> 6996488.5 | F23: =SUMIFS('Data Pembelian untuk Operasiona'!$D:$D,'Data Pembelian untuk Operasiona'!$E:$E,"SPK",'Data Pembelian untuk Operasiona'!$A:$A,"March 2025") -> 6470698 | G23: =SUMIFS('Data Pembelian untuk Operasiona'!$D:$D,'Data Pembelian untuk Operasiona'!$E:$E,"SPK",'Data Pembelian untuk Operasiona'!$A:$A,"April 2025") -> 5301080 | H23: =SUMIFS('Data Pembelian untuk Operasiona'!$D:$D,'Data Pembelian untuk Operasiona'!$E:$E,"SPK",'Data Pembelian untuk Operasiona'!$A:$A,"May 2025") -> 6715272.8 | I23: =SUMIFS('Data Pembelian untuk Operasiona'!$D:$D,'Data Pembelian untuk Operasiona'!$E:$E,"SPK",'Data Pembelian untuk Operasiona'!$A:$A,"June 2025") -> 7234716.5 | J23: =SUM(D23:I23) -> 40180562
B24: 2 | C24: Operasional | D24: =SUMIFS('Data Pembelian untuk Operasiona'!$D:$D,'Data Pembelian untuk Operasiona'!$E:$E,"Operasional",'Data Pembelian untuk Operasiona'!$A:$A,"January 2025") -> 2230682.4 | E24: =SUMIFS('Data Pembelian untuk Operasiona'!$D:$D,'Data Pembelian untuk Operasiona'!$E:$E,"Operasional",'Data Pembelian untuk Operasiona'!$A:$A,"February 2025") -> 1908186.6 | F24: =SUMIFS('Data Pembelian untuk Operasiona'!$D:$D,'Data Pembelian untuk Operasiona'!$E:$E,"Operasional",'Data Pembelian untuk Operasiona'!$A:$A,"March 2025") -> 1149480.5 | G24: =SUMIFS('Data Pembelian untuk Operasiona'!$D:$D,'Data Pembelian untuk Operasiona'!$E:$E,"Operasional",'Data Pembelian untuk Operasiona'!$A:$A,"April 2025") -> 1441507.6 | H24: =SUMIFS('Data Pembelian untuk Operasiona'!$D:$D,'Data Pembelian untuk Operasiona'!$E:$E,"Operasional",'Data Pembelian untuk Operasiona'!$A:$A,"May 2025") -> 1396591.8 | I24: =SUMIFS('Data Pembelian untuk Operasiona'!$D:$D,'Data Pembelian untuk Operasiona'!$E:$E,"Operasional",'Data Pembelian untuk Operasiona'!$A:$A,"June 2025") -> 1688899.5 | J24: =SUM(D24:I24) -> 9815348.5
B25: 3 | C25: Inventory | D25: =SUMIFS('Data Pembelian untuk Operasiona'!$D:$D,'Data Pembelian untuk Operasiona'!$E:$E,"Inventory",'Data Pembelian untuk Operasiona'!$A:$A,"January 2025") -> 328282 | E25: =SUMIFS('Data Pembelian untuk Operasiona'!$D:$D,'Data Pembelian untuk Operasiona'!$E:$E,"Inventory",'Data Pembelian untuk Operasiona'!$A:$A,"February 2025") -> 328498.8 | F25: =SUMIFS('Data Pembelian untuk Operasiona'!$D:$D,'Data Pembelian untuk Operasiona'!$E:$E,"Inventory",'Data Pembelian untuk Operasiona'!$A:$A,"March 2025") -> 281924.5 | G25: =SUMIFS('Data Pembelian untuk Operasiona'!$D:$D,'Data Pembelian untuk Operasiona'!$E:$E,"Inventory",'Data Pembelian untuk Operasiona'!$A:$A,"April 2025") -> 363305 | H25: =SUMIFS('Data Pembelian untuk Operasiona'!$D:$D,'Data Pembelian untuk Operasiona'!$E:$E,"Inventory",'Data Pembelian untuk Operasiona'!$A:$A,"May 2025") -> 479600 | I25: =SUMIFS('Data Pembelian untuk Operasiona'!$D:$D,'Data Pembelian untuk Operasiona'!$E:$E,"Inventory",'Data Pembelian untuk Operasiona'!$A:$A,"June 2025") -> 479647.5 | J25: =SUM(D25:I25) -> 2261257.8
B27: Transportasi | D27: =SUMIFS('Data Reimburse Transport'!$C:$C,'Data Reimburse Transport'!$B:$B,"January 2025") -> 1884250 | E27: =SUMIFS('Data Reimburse Transport'!$C:$C,'Data Reimburse Transport'!$B:$B,"February 2025") -> 1890875 | F27: =SUMIFS('Data Reimburse Transport'!$C:$C,'Data Reimburse Transport'!$B:$B,"March 2025") -> 1875650 | G27: =SUMIFS('Data Reimburse Transport'!$C:$C,'Data Reimburse Transport'!$B:$B,"April 2025") -> 1849025 | H27: =SUMIFS('Data Reimburse Transport'!$C:$C,'Data Reimburse Transport'!$B:$B,"May 2025") -> 2072225 | I27: =SUMIFS('Data Reimburse Transport'!$C:$C,'Data Reimburse Transport'!$B:$B,"June 2025") -> 2122200 | J27: =SUM(D27:I27) -> 11694225
B28: Benefit Lainnya | D28: =SUMIFS('Data Gaji'!$D:$D,'Data Gaji'!$A:$A,"January 2025") -> 3309857.7 | E28: =SUMIFS('Data Gaji'!$D:$D,'Data Gaji'!$A:$A,"February 2025") -> 3419120.2 | F28: =SUMIFS('Data Gaji'!$D:$D,'Data Gaji'!$A:$A,"March 2025") -> 3496096.5 | G28: =SUMIFS('Data Gaji'!$D:$D,'Data Gaji'!$A:$A,"April 2025") -> 3773669.7 | H28: =SUMIFS('Data Gaji'!$D:$D,'Data Gaji'!$A:$A,"May 2025") -> 4067215.8 | I28: =SUMIFS('Data Gaji'!$D:$D,'Data Gaji'!$A:$A,"June 2025") -> 4301273.3 | J28: =SUM(D28:I28) -> 22367233
B29: THR | D29: =SUMIFS('Data Gaji'!$E:$E,'Data Gaji'!$A:$A,"January 2025") -> 919404.91 | E29: =SUMIFS('Data Gaji'!$E:$E,'Data Gaji'!$A:$A,"February 2025") -> 949755.6 | F29: =SUMIFS('Data Gaji'!$E:$E,'Data Gaji'!$A:$A,"March 2025") -> 971137.93 | G29: =SUMIFS('Data Gaji'!$E:$E,'Data Gaji'!$A:$A,"April 2025") -> 1048241.6 | H29: =SUMIFS('Data Gaji'!$E:$E,'Data Gaji'!$A:$A,"May 2025") -> 1129782.2 | I29: =SUMIFS('Data Gaji'!$E:$E,'Data Gaji'!$A:$A,"June 2025") -> 1194798.1 | J29: =SUM(D29:I29) -> 6213120.3
B31: Total Biaya | D31: =SUM(D14,D22,D27:D29) -> 27167643 | E31: =SUM(E14,E22,E27:E29) -> 26889992 | F31: =SUM(F14,F22,F27:F29) -> 25898643 | G31: =SUM(G14,G22,G27:G29) -> 26355728 | H31: =SUM(H14,H22,H27:H29) -> 29418073 | I31: =SUM(I14,I22,I27:I29) -> 31359112 | J31: =SUM(D31:I31) -> 1.6708919e+08
B32: Laba / Rugi (EBITDA) | D32: =D5-D31 -> 2391457 | E32: =E5-E31 -> 450688.92 | F32: =F5-F31 -> -289992.63 | G32: =G5-G31 -> 1654791.5 | H32: =H5-H31 -> 3856868.2 | I32: =I5-I31 -> -4661662.4 | J32: =SUM(D32:I32) -> 3402150.6
B34: Net Profit Margin | D34: =(D32/D5)*100% -> 0.080904259 | E34: =(E32/E5)*100% -> 0.016484188 | F34: =(F32/F5)*100% -> -0.011324011 | G34: =(G32/G5)*100% -> 0.0590775 | H34: =(H32/H5)*100% -> 0.11590909 | I34: =(I32/I5)*100% -> -0.17461078 | J34: =SUM(D34:I34) -> 0.08644025

Sheet Data Penjualan
A1: Nomor Invoice | B1: Bulan | C1: Kategori Penjualan | D1: Harga | E1: Status
A2: 1 | B2: April 2025 | C2: Fixing | D2: 12500 | E2: Sudah Dibayar | I2: Row Labels | J2: Sum of Harga
A3: 2 | B3: April 2025 | C3: Lainnya | D3: 7500 | E3: Sudah Dibayar | I3: April 2025 | J3: 28010520
A4: 3 | B4: April 2025 | C4: Cleaning | D4: 10000 | E4: Sudah Dibayar | I4: AC | J4: 2141750
A5: 4 | B5: April 2025 | C5: Fixing | D5: 5000 | E5: Sudah Dibayar | I5: Cleaning | J5: 3686250
A6: 5 | B6: April 2025 | C6: AC | D6: 7500 | E6: Sudah Dibayar | I6: Field Assistant | J6: 8196000
A7: 6 | B7: April 2025 | C7: AC | D7: 3750 | E7: Sudah Dibayar | I7: Fixing | J7: 4145619.5
A8: 7 | B8: April 2025 | C8: Fixing | D8: 11000 | E8: Sudah Dibayar | I8: Lainnya | J8: 897500
A9: 8 | B9: April 2025 | C9: Material | D9: 10500 | E9: Sudah Dibayar | I9: Material | J9: 8018400
A10: 9 | B10: April 2025 | C10: Material | D10: 500 | E10: Sudah Dibayar | I10: Photographer | J10: 925000
A11: 10 | B11: April 2025 | C11: Material | D11: 3500 | E11: Sudah Dibayar | I11: February 2025 | J11: 27340681
A12: 11 | B12: April 2025 | C12: Material | D12: 750 | E12: Sudah Dibayar | I12: AC | J12: 2027500
A13: 12 | B13: April 2025 | C13: Material | D13: 4250 | E13: Sudah Dibayar | I13: Cleaning | J13: 3862500
A14: 13 | B14: April 2025 | C14: AC | D14: 15000 | E14: Sudah Dibayar | I14: Field Assistant | J14: 9036000
... A51: 50 | B51: April 2025 | C51: Material | D51: 11500 | E51: Belum Dibayar | I51: Grand Total | J51: 1.7049134e+08
A52: 51 | B52: April 2025 | C52: Material | D52: 7500 | E52: Belum Dibayar
A53: 52 | B53: April 2025 | C53: AC | D53: 5000 | E53: Belum Dibayar
A54: 53 | B54: April 2025 | C54: Cleaning | D54: 8750 | E54: Sudah Dibayar
A55: 54 | B55: April 2025 | C55: AC | D55: 11250 | E55: Sudah Dibayar
A56: 55 | B56: April 2025 | C56: Cleaning | D56: 12500 | E56: Sudah Dibayar
A57: 56 | B57: April 2025 | C57: Lainnya | D57: 4750 | E57: Sudah Dibayar
A58: 57 | B58: April 2025 | C58: Fixing | D58: 5000 | E58: Sudah Dibayar
A59: 58 | B59: April 2025 | C59: Material | D59: 2500 | E59: Sudah Dibayar
A60: 59 | B60: April 2025 | C60: Fixing | D60: 7500 | E60: Sudah Dibayar
A61: 60 | B61: April 2025 | C61: Material | D61: 1500 | E61: Sudah Dibayar
A62: 61 | B62: April 2025 | C62: Material | D62: 5500 | E62: Sudah Dibayar
A63: 62 | B63: April 2025 | C63: Material | D63: 1750 | E63: Sudah Dibayar
... A12362: 12361 | B12362: May 2025 | C12362: Photographer | D12362: 510000 | E12362: Sudah Dibayar

Sheet Data Pembelian untuk Operasiona
A1: Bulan | B1: Nomor Transaksi | C1: Nama Produk | D1: Harga | E1: Kategori Pembelian
A2: January 2025 | B2: 38522 | C2: Material Perbaikan Unit | D2: 11500 | E2: SPK | G2: Row Labels | H2: Sum of Harga
A3: January 2025 | B3: 38523 | C3: Material Perbaikan Unit | D3: 2250 | E3: SPK | G3: April 2025 | H3: 7105892.6
A4: January 2025 | B4: 38524 | C4: Material Perbaikan Unit | D4: 6300 | E4: SPK | G4: Inventory | H4: 363305
A5: January 2025 | B5: 38525 | C5: Material Perbaikan Unit | D5: 1750 | E5: SPK | G5: Operasional | H5: 1441507.6
A6: January 2025 | B6: 38526 | C6: Material Perbaikan Unit | D6: 20900 | E6: SPK | G6: SPK | H6: 5301080
A7: January 2025 | B7: 38527 | C7: Material Perbaikan Unit | D7: 5500 | E7: SPK | G7: February 2025 | H7: 9233173.9
A8: January 2025 | B8: 38528 | C8: Material Perbaikan Unit | D8: 250 | E8: SPK | G8: Inventory | H8: 328498.8
A9: January 2025 | B9: 38528 | C9: Material Perbaikan Unit | D9: 250 | E9: SPK | G9: Operasional | H9: 1908186.6
A10: January 2025 | B10: 38528 | C10: Material Perbaikan Unit | D10: 650 | E10: SPK | G10: SPK | H10: 6996488.5
A11: January 2025 | B11: 38528 | C11: Material Perbaikan Unit | D11: 1750 | E11: SPK | G11: January 2025 | H11: 10021271
A12: January 2025 | B12: 38528 | C12: Material Perbaikan Unit | D12: 4250 | E12: SPK | G12: Inventory | H12: 328282
A13: January 2025 | B13: 38529 | C13: Material Perbaikan Unit | D13: 12293 | E13: SPK | G13: Operasional | H13: 2230682.4
A14: January 2025 | B14: 38530 | C14: Material Perbaikan Unit | D14: 500 | E14: SPK | G14: SPK | H14: 7462306.6
... A27: January 2025 | B27: 38536 | C27: Inventory | D27: 500 | E27: Inventory | G27: Grand Total | H27: 52257169
A28: January 2025 | B28: 38537 | C28: Material Perbaikan Unit | D28: 5250 | E28: SPK
A29: January 2025 | B29: 38538 | C29: Material Perbaikan Unit | D29: 250 | E29: SPK
A30: January 2025 | B30: 38539 | C30: Material Perbaikan Unit | D30: 5500 | E30: SPK
A31: January 2025 | B31: 38540 | C31: Material Perbaikan Unit | D31: 7250 | E31: SPK
A32: January 2025 | B32: 38540 | C32: Material Perbaikan Unit | D32: 250 | E32: SPK
A33: January 2025 | B33: 38541 | C33: Material Perbaikan Unit | D33: 6000 | E33: SPK
A34: January 2025 | B34: 38541 | C34: Material Perbaikan Unit | D34: 500 | E34: SPK
A35: January 2025 | B35: 38541 | C35: Material Perbaikan Unit | D35: 1000 | E35: SPK
A36: January 2025 | B36: 38542 | C36: Material Perbaikan Unit | D36: 28000 | E36: SPK
A37: January 2025 | B37: 38542 | C37: Material Perbaikan Unit | D37: 750 | E37: SPK
A38: January 2025 | B38: 38543 | C38: Inventory | D38: 3500 | E38: Inventory
A39: January 2025 | B39: 38544 | C39: Perlengkapan AC | D39: 8505 | E39: Operasional
... A9372: June 2025 | B9372: 43744 | C9372: Perlengkapan Cleaning | D9372: 57546.25 | E9372: Operasional

Sheet Data Gaji
A1: Bulan | B1: Nama Karyawan | C1: Gaji | D1: Benefit Lainnya | E1: THR (Prorate) | F1: Divisi
A2: January 2025 | B2: 1 | C2: 507055.95 | D2: 152116.79 | E2: 42254.662 | F2: Admin | H2: Row Labels | I2: Sum of Gaji | J2: Sum of Benefit Lainnya | K2: Sum of THR (Prorate)
A3: January 2025 | B3: 2 | C3: 262558.45 | D3: 78767.535 | E3: 21879.871 | F3: Admin | H3: April 2025 | I3: 12578899 | J3: 3773669.7 | K3: 1048241.6
A4: January 2025 | B4: 3 | C4: 222206.5 | D4: 66661.95 | E4: 18517.208 | F4: Teknisi AC | H4: Admin | I4: 1272670.4 | J4: 381801.14 | K4: 106055.87
A5: January 2025 | B5: 4 | C5: 234456.5 | D5: 70336.95 | E5: 19538.042 | F5: Asisten Lapangan | H5: Asisten Lapangan | I5: 3876571.7 | J5: 1162971.5 | K5: 323047.65
A6: January 2025 | B6: 5 | C6: 141206.5 | D6: 42361.95 | E6: 11767.208 | F6: Teknisi AC | H6: Fotografer | I6: 551464.5 | J6: 165439.35 | K6: 45955.375
A7: January 2025 | B7: 6 | C7: 248282.5 | D7: 74484.75 | E7: 20690.208 | F7: Asisten Lapangan | H7: Teknisi AC | I7: 2578300.2 | J7: 773490.07 | K7: 214858.35
A8: January 2025 | B8: 7 | C8: 238706.5 | D8: 71611.95 | E8: 19892.208 | F8: Asisten Lapangan | H8: Teknisi Kebersihan | I8: 1506422.8 | J8: 451926.82 | K8: 125535.23
A9: January 2025 | B9: 8 | C9: 139625.85 | D9: 41887.755 | E9: 11635.488 | F9: Teknisi Kebersihan | H9: Teknisi Perbaikan | I9: 2793469.4 | J9: 838040.83 | K9: 232789.12
A10: January 2025 | B10: 9 | C10: 214206.5 | D10: 64261.95 | E10: 17850.542 | F10: Teknisi Kebersihan | H10: February 2025 | I10: 11397067 | J10: 3419120.2 | K10: 949755.6
A11: January 2025 | B11: 10 | C11: 132222.6 | D11: 39666.78 | E11: 11018.55 | F11: Teknisi Perbaikan | H11: Admin | I11: 1336090.3 | J11: 400827.08 | K11: 111340.86
A12: January 2025 | B12: 11 | C12: 130045.2 | D12: 39013.56 | E12: 10837.1 | F12: Teknisi Kebersihan | H12: Asisten Lapangan | I12: 3591611.5 | J12: 1077483.5 | K12: 299300.96
A13: January 2025 | B13: 12 | C13: 117706.5 | D13: 35311.95 | E13: 9808.875 | F13: Teknisi AC | H13: Fotografer | I13: 356654.9 | J13: 106996.47 | K13: 29721.242
A14: January 2025 | B14: 13 | C14: 243174.2 | D14: 72952.26 | E14: 20264.517 | F14: Teknisi AC | H14: Teknisi AC | I14: 2395768.1 | J14: 718730.43 | K14: 199647.34
... A45: January 2025 | B45: 44 | C45: 116206.5 | D45: 34861.95 | E45: 9683.875 | F45: Teknisi AC | H45: Grand Total | I45: 74557444 | J45: 22367233 | K45: 6213120.3
A46: January 2025 | B46: 45 | C46: 130335.5 | D46: 39100.65 | E46: 10861.292 | F46: Admin
A47: January 2025 | B47: 46 | C47: 116206.5 | D47: 34861.95 | E47: 9683.875 | F47: Teknisi AC
A48: January 2025 | B48: 47 | C48: 222206.5 | D48: 66661.95 | E48: 18517.208 | F48: Asisten Lapangan
A49: January 2025 | B49: 48 | C49: 118980.65 | D49: 35694.195 | E49: 9915.0542 | F49: Teknisi Kebersihan
A50: January 2025 | B50: 49 | C50: 167706.5 | D50: 50311.95 | E50: 13975.542 | F50: Teknisi Perbaikan
A51: January 2025 | B51: 50 | C51: 116206.5 | D51: 34861.95 | E51: 9683.875 | F51: Teknisi AC
A52: January 2025 | B52: 51 | C52: 166206.5 | D52: 49861.95 | E52: 13850.542 | F52: Teknisi AC
A53: January 2025 | B53: 52 | C53: 141206.5 | D53: 42361.95 | E53: 11767.208 | F53: Teknisi AC
A54: January 2025 | B54: 53 | C54: 229706.5 | D54: 68911.95 | E54: 19142.208 | F54: Asisten Lapangan
A55: January 2025 | B55: 54 | C55: 167706.5 | D55: 50311.95 | E55: 13975.542 | F55: Teknisi Perbaikan
A56: January 2025 | B56: 55 | C56: 175206.5 | D56: 52561.95 | E56: 14600.542 | F56: Fotografer
A57: January 2025 | B57: 56 | C57: 220287.1 | D57: 66086.13 | E57: 18357.258 | F57: Asisten Lapangan
... A450: June 2025 | B450: 104 | C450: 10483.85 | D450: 3145.155 | E450: 873.65417 | F450: Teknisi Kebersihan

Sheet Data Reimburse Transport
A1: Kode Reimburse | B1: Bulan | C1: Nilai Reimburse
A2: 123-1 | B2: January 2025 | C2: 975
A3: 123-2 | B3: January 2025 | C3: 875 | E3: Row Labels | F3: Sum of Nilai Reimburse
A4: 123-3 | B4: January 2025 | C4: 725 | E4: April 2025 | F4: 1849025
A5: 123-4 | B5: January 2025 | C5: 550 | E5: February 2025 | F5: 1890875
A6: 123-5 | B6: January 2025 | C6: 375 | E6: January 2025 | F6: 1884250
A7: 123-6 | B7: January 2025 | C7: 975 | E7: June 2025 | F7: 2122200
A8: 123-7 | B8: January 2025 | C8: 675 | E8: March 2025 | F8: 1875650
A9: 123-8 | B9: January 2025 | C9: 625 | E9: May 2025 | F9: 2072225
A10: 123-9 | B10: January 2025 | C10: 1000 | E10: Grand Total | F10: 11694225
A11: 123-10 | B11: January 2025 | C11: 850
A12: 123-11 | B12: January 2025 | C12: 300
A13: 123-12 | B13: January 2025 | C13: 450
A14: 123-13 | B14: January 2025 | C14: 575
A15: 123-14 | B15: January 2025 | C15: 700
A16: 123-15 | B16: January 2025 | C16: 525
A17: 123-16 | B17: January 2025 | C17: 600
A18: 123-17 | B18: January 2025 | C18: 725
A19: 123-18 | B19: January 2025 | C19: 500
A20: 123-19 | B20: January 2025 | C20: 450
A21: 123-20 | B21: January 2025 | C21: 650
A22: 123-21 | B22: January 2025 | C22: 475
... A24586: 123-24585 | B24586: June 2025 | C24586: 925
